quditto_client/interfaces_pb2.py
quditto_client/interfaces_pb2_grpc.py
quditto_client/quditto_etsi_004_client.py
quditto_client-0.2.1.dist-info/METADATA
quditto_client-0.2.1.dist-info/WHEEL
quditto_client-0.2.1.dist-info/RECORD
